taskc/__init__.py
taskc/errors.py
taskc/fixture/.taskrc
taskc/fixture/pki/README
taskc/fixture/pki/ca.cert.pem
taskc/fixture/pki/ca.key.pem
taskc/fixture/pki/ca.template
taskc/fixture/pki/check_expire
taskc/fixture/pki/client.cert.pem
taskc/fixture/pki/client.key.pem
taskc/fixture/pki/client.template
taskc/fixture/pki/crl.template
taskc/fixture/pki/generate
taskc/fixture/pki/generate.ca
taskc/fixture/pki/generate.client
taskc/fixture/pki/generate.crl
taskc/fixture/pki/generate.server
taskc/fixture/pki/server.cert.pem
taskc/fixture/pki/server.crl.pem
taskc/fixture/pki/server.key.pem
taskc/fixture/pki/server.template
taskc/fixture/pki/vars
taskc/fixture/taskdresponse.txt
taskc/simple.py
taskc/test_simple.py
taskc/test_transaction.py
taskc/transaction.py
taskc-0.2.0.dist-info/LICENSE
taskc-0.2.0.dist-info/WHEEL
taskc-0.2.0.dist-info/METADATA
taskc-0.2.0.dist-info/RECORD
